README.txt
setup.py
Products/__init__.py
Products.DigestoContentTypes.egg-info/PKG-INFO
Products.DigestoContentTypes.egg-info/SOURCES.txt
Products.DigestoContentTypes.egg-info/dependency_links.txt
Products.DigestoContentTypes.egg-info/entry_points.txt
Products.DigestoContentTypes.egg-info/namespace_packages.txt
Products.DigestoContentTypes.egg-info/not-zip-safe
Products.DigestoContentTypes.egg-info/requires.txt
Products.DigestoContentTypes.egg-info/top_level.txt
Products/DigestoContentTypes/__init__.py
Products/DigestoContentTypes/config.py
Products/DigestoContentTypes/configure.zcml
Products/DigestoContentTypes/localroles.py
Products/DigestoContentTypes/permissions.py
Products/DigestoContentTypes/profiles.zcml
Products/DigestoContentTypes/refresh.txt
Products/DigestoContentTypes/setuphandlers.py
Products/DigestoContentTypes/version.txt
Products/DigestoContentTypes/Extensions/Install.py
Products/DigestoContentTypes/Extensions/__init__.py
Products/DigestoContentTypes/browser/__init__.py
Products/DigestoContentTypes/browser/area.py
Products/DigestoContentTypes/browser/configure.zcml
Products/DigestoContentTypes/browser/interfaces.py
Products/DigestoContentTypes/browser/ksscommands.py
Products/DigestoContentTypes/browser/manage_abbreviations.pt
Products/DigestoContentTypes/browser/searchtools.py
Products/DigestoContentTypes/browser/typescontrolpanel.py
Products/DigestoContentTypes/browser/typestools.py
Products/DigestoContentTypes/browser/widget.py
Products/DigestoContentTypes/browser/resources/digestocontenttypes.css
Products/DigestoContentTypes/browser/resources/digestocontenttypes.kss
Products/DigestoContentTypes/browser/resources/normativalivesearch.js
Products/DigestoContentTypes/browser/resources/sequence.js
Products/DigestoContentTypes/browser/resources/type_settings_icon.gif
Products/DigestoContentTypes/browser/templates/widget.pt
Products/DigestoContentTypes/content/Area.py
Products/DigestoContentTypes/content/Attachment.py
Products/DigestoContentTypes/content/Normativa.py
Products/DigestoContentTypes/content/__init__.py
Products/DigestoContentTypes/content/configure.zcml
Products/DigestoContentTypes/content/interfaces.py
Products/DigestoContentTypes/i18n/DigestoContentTypes-es-plone.po
Products/DigestoContentTypes/i18n/DigestoContentTypes-es.po
Products/DigestoContentTypes/i18n/DigestoContentTypes-plone.pot
Products/DigestoContentTypes/i18n/DigestoContentTypes.pot
