Metadata-Version: 1.0
Name: Products.DigestoContentTypes
Version: 1.2a1
Summary: Plone content types for legislative documents
Home-page: http://plone.org/products/digestocontenttypes/
Author: Emanuel Sartor, Santiago Bruno
Author-email: info@menttes.com
License: GPL
Keywords: web zope plone
Platform: UNKNOWN
Classifier: Framework :: Plone
Classifier: Programming Language :: Python
Classifier: Topic :: Software Development :: Libraries :: Python Modules
